{
  "modules": [
    {
      "type": "tconstruct:part_stats",
      "parts": [
        "tconstruct:pick_head",
        "tinkersancient:war_pick_limb",
        "tinkersancient:war_pick_handle",
        "tconstruct:bowstring"
      ],
      "primary_part": 0
    },
    {
      "type": "tconstruct:default_materials",
      "materials": [
        {
          "type": "tconstruct:random",
          "tier": 1
        },
        {
          "type": "tconstruct:random",
          "tier": 1
        },
        {
          "type": "tconstruct:random",
          "tier": 1
        },
        {
          "type": "tconstruct:random",
          "tier": 1
        }
      ]
    },
    {
      "type": "tconstruct:material_traits",
      "hooks": [
        "tconstruct:tool_traits",
        "tconstruct:rebalanced_trait"
      ],
      "material_index": 0,
      "stat_type": "tconstruct:head"
    },
    {
      "type": "tconstruct:material_traits",
      "hooks": [
        "tconstruct:tool_traits",
        "tconstruct:rebalanced_trait"
      ],
      "material_index": 1,
      "stat_type": "tconstruct:limb"
    },
    {
      "type": "tconstruct:base_stats",
      "stats": {
        "tconstruct:attack_speed": 1.2,
        "tconstruct:durability": 200,
        "tconstruct:accuracy": 2,
        "tconstruct:draw_speed": 1.6
      }
    },
    {
      "type": "tconstruct:multiply_stats",
      "multipliers": {
        "tconstruct:draw_speed": 1.4,
        "tconstruct:mining_speed": 1.3
      }
    },
    {
      "type": "tconstruct:modifier_slots",
      "slots": {
        "abilities": 1,
        "upgrades": 3
      }
    },
    {
      "type": "tconstruct:tool_actions",
      "tool_actions": [
        "pickaxe_dig"
      ]
    },
    {
      "type": "tconstruct:is_effective",
      "predicate_type": "mantle:tag",
      "tag": "minecraft:mineable/pickaxe"
    },
    {
      "type": "tconstruct:circle_aoe",
      "3D": false,
      "diameter": 1
    }
  ]
}